{"frames": {"default": [{"frame_name": "fx_f4_daemoniclure_000.png", "x0": 352, "y0": 704, "x1": 527, "y1": 879, "width": 175, "height": 175}, {"frame_name": "fx_f4_daemoniclure_001.png", "x0": 880, "y0": 528, "x1": 1055, "y1": 703, "width": 175, "height": 175}, {"frame_name": "fx_f4_daemoniclure_002.png", "x0": 880, "y0": 352, "x1": 1055, "y1": 527, "width": 175, "height": 175}, {"frame_name": "fx_f4_daemoniclure_003.png", "x0": 880, "y0": 176, "x1": 1055, "y1": 351, "width": 175, "height": 175}, {"frame_name": "fx_f4_daemoniclure_004.png", "x0": 880, "y0": 0, "x1": 1055, "y1": 175, "width": 175, "height": 175}, {"frame_name": "fx_f4_daemoniclure_005.png", "x0": 704, "y0": 704, "x1": 879, "y1": 879, "width": 175, "height": 175}, {"frame_name": "fx_f4_daemoniclure_006.png", "x0": 704, "y0": 528, "x1": 879, "y1": 703, "width": 175, "height": 175}, {"frame_name": "fx_f4_daemoniclure_007.png", "x0": 704, "y0": 352, "x1": 879, "y1": 527, "width": 175, "height": 175}, {"frame_name": "fx_f4_daemoniclure_008.png", "x0": 704, "y0": 176, "x1": 879, "y1": 351, "width": 175, "height": 175}, {"frame_name": "fx_f4_daemoniclure_009.png", "x0": 704, "y0": 0, "x1": 879, "y1": 175, "width": 175, "height": 175}, {"frame_name": "fx_f4_daemoniclure_010.png", "x0": 528, "y0": 704, "x1": 703, "y1": 879, "width": 175, "height": 175}, {"frame_name": "fx_f4_daemoniclure_011.png", "x0": 528, "y0": 528, "x1": 703, "y1": 703, "width": 175, "height": 175}, {"frame_name": "fx_f4_daemoniclure_012.png", "x0": 528, "y0": 352, "x1": 703, "y1": 527, "width": 175, "height": 175}, {"frame_name": "fx_f4_daemoniclure_013.png", "x0": 528, "y0": 176, "x1": 703, "y1": 351, "width": 175, "height": 175}, {"frame_name": "fx_f4_daemoniclure_014.png", "x0": 528, "y0": 0, "x1": 703, "y1": 175, "width": 175, "height": 175}, {"frame_name": "fx_f4_daemoniclure_015.png", "x0": 880, "y0": 704, "x1": 1055, "y1": 879, "width": 175, "height": 175}, {"frame_name": "fx_f4_daemoniclure_016.png", "x0": 352, "y0": 528, "x1": 527, "y1": 703, "width": 175, "height": 175}, {"frame_name": "fx_f4_daemoniclure_017.png", "x0": 352, "y0": 352, "x1": 527, "y1": 527, "width": 175, "height": 175}, {"frame_name": "fx_f4_daemoniclure_018.png", "x0": 352, "y0": 176, "x1": 527, "y1": 351, "width": 175, "height": 175}, {"frame_name": "fx_f4_daemoniclure_019.png", "x0": 352, "y0": 0, "x1": 527, "y1": 175, "width": 175, "height": 175}, {"frame_name": "fx_f4_daemoniclure_020.png", "x0": 176, "y0": 704, "x1": 351, "y1": 879, "width": 175, "height": 175}, {"frame_name": "fx_f4_daemoniclure_021.png", "x0": 176, "y0": 528, "x1": 351, "y1": 703, "width": 175, "height": 175}, {"frame_name": "fx_f4_daemoniclure_022.png", "x0": 176, "y0": 352, "x1": 351, "y1": 527, "width": 175, "height": 175}, {"frame_name": "fx_f4_daemoniclure_023.png", "x0": 176, "y0": 176, "x1": 351, "y1": 351, "width": 175, "height": 175}, {"frame_name": "fx_f4_daemoniclure_024.png", "x0": 176, "y0": 0, "x1": 351, "y1": 175, "width": 175, "height": 175}, {"frame_name": "fx_f4_daemoniclure_025.png", "x0": 0, "y0": 704, "x1": 175, "y1": 879, "width": 175, "height": 175}, {"frame_name": "fx_f4_daemoniclure_026.png", "x0": 0, "y0": 528, "x1": 175, "y1": 703, "width": 175, "height": 175}, {"frame_name": "fx_f4_daemoniclure_027.png", "x0": 0, "y0": 352, "x1": 175, "y1": 527, "width": 175, "height": 175}, {"frame_name": "fx_f4_daemoniclure_028.png", "x0": 0, "y0": 176, "x1": 175, "y1": 351, "width": 175, "height": 175}, {"frame_name": "fx_f4_daemoniclure_029.png", "x0": 0, "y0": 0, "x1": 175, "y1": 175, "width": 175, "height": 175}]}, "texture_filename": "fx_f4_daemoniclure.png", "width": 2048, "height": 1024}